{
    "title": "Magic Titles Namelist",
    "description": "Wizard ranks (Archmage, etc).",
    "generic": {
        "male": [
            "Enchanter",
            "Grand Sorcerer",
            "Headmaster",
            "High Enchanter",
            "Seer",
            "Sorcerer"
        ],
        "female": [
            "Enchantress",
            "Grand Sorceress",
            "Headmistress",
            "High Enchantress",
            "Seeress",
            "Sorceress",
            "Witch"
        ],
        "neutral": [
            "Abjurist",
            "Adept",
            "Adeptus Major",
            "Adeptus Minor",
            "Alchemist",
            "Apprentice",
            "Arch-Magi",
            "Archimedean",
            "Archmage",
            "Archmagus",
            "Astrologer",
            "Augur",
            "Battlemage",
            "Conjurer",
            "Evoker",
            "Hedge Wizard",
            "High",
            "High Magus",
            "Illusionist",
            "Journeymage",
            "Magister",
            "Magus",
            "Necromancer",
            "Neophyte",
            "Novice",
            "Professor",
            "Scholar",
            "Thaumaturgist",
            "Theurgist",
            "Warlock",
            "Wizard",
            "Archivist"
        ]
    }
}